README.rst
setup.cfg
setup.py
almanac/__init__.py
almanac/exceptions.py
almanac/registry.py
his.almanac.egg-info/PKG-INFO
his.almanac.egg-info/SOURCES.txt
his.almanac.egg-info/dependency_links.txt
his.almanac.egg-info/top_level.txt
tests/__init__.py
tests/test_registry.py