Metadata-Version: 1.1
Name: his.almanac
Version: 0.0.1
Summary: A services registry
Home-page: UNKNOWN
Author: Jonathan Moss
Author-email: xirisr@gmail.com
License: BSD
Keywords: registry
Platform: linux
Classifier: Development Status :: 2 - Pre-Alpha
Classifier: Intended Audience :: Developers
Classifier: License :: OSI Approved :: BSD License
Classifier: Operating System :: Unix
Classifier: Programming Language :: Python
Classifier: Programming Language :: Python :: 3.6
Classifier: Topic :: Other/Nonlisted Topic
